pypck/__init__.py
pypck/connection.py
pypck/device.py
pypck/helpers.py
pypck/inputs.py
pypck/lcn_addr.py
pypck/lcn_defs.py
pypck/pck_commands.py
pypck/py.typed
pypck/status_requester.py
pypck-0.9.9.dist-info/licenses/LICENSE
pypck-0.9.9.dist-info/METADATA
pypck-0.9.9.dist-info/WHEEL
pypck-0.9.9.dist-info/top_level.txt
pypck-0.9.9.dist-info/RECORD
