Metadata-Version: 2.4
Name: pypck
Version: 0.9.9
Summary: LCN-PCK library
Home-page: https://github.com/alengwenus/pypck
Author-email: Andre Lengwenus <alengwenus@gmail.com>
License: MIT
Project-URL: Source Code, https://github.com/alengwenus/pypck
Project-URL: Bug Reports, https://github.com/alengwenus/pypck/issues
Keywords: lcn,pck
Platform: any
Classifier: Programming Language :: Python :: 3
Classifier: License :: OSI Approved :: MIT License
Classifier: Intended Audience :: Developers
Classifier: Development Status :: 5 - Production/Stable
Classifier: Operating System :: OS Independent
Classifier: Topic :: Home Automation
Requires-Python: >=3.11
License-File: LICENSE
Dynamic: license-file
